ojpacker/__init__.py
ojpacker/__main__.py
ojpacker/arg.py
ojpacker/config.py
ojpacker/demo.py
ojpacker/entrance.py
ojpacker/error.py
ojpacker/filetype.py
ojpacker/garbage.py
ojpacker/ui.py
ojpacker/utiliy.py
ojpacker/work_compile.py
ojpacker/work_in.py
ojpacker/work_out.py
ojpacker/work_zip.py
ojpacker/workflow.py
ojpacker-0.1.5.dist-info/LICENSE
ojpacker-0.1.5.dist-info/METADATA
ojpacker-0.1.5.dist-info/WHEEL
ojpacker-0.1.5.dist-info/entry_points.txt
ojpacker-0.1.5.dist-info/top_level.txt
ojpacker-0.1.5.dist-info/RECORD
