Metadata-Version: 2.1
Name: ojpacker
Version: 0.1.5
Summary: a script can packer test data for Olympic informatics Online Judge
Home-page: https://github.com/Simon-Chenzw/OJpacker
Author: Simon_Chen
Author-email: 1020359403@qq.com
License: GNU Lesser General Public License v3 (LGPLv3)
Platform: UNKNOWN
Classifier: Development Status :: 3 - Alpha
Classifier: License :: OSI Approved :: GNU Lesser General Public License v3 (LGPLv3)
Classifier: Programming Language :: Python :: 3.6
Classifier: Programming Language :: Python :: Implementation :: CPython
Requires-Python: >=3.6.9
Requires-Dist: rich (>=4.1)
